sridentify/__init__.py
sridentify/cli.py
sridentify/epsg.db
sridentify-0.4.0.dist-info/DESCRIPTION.rst
sridentify-0.4.0.dist-info/METADATA
sridentify-0.4.0.dist-info/RECORD
sridentify-0.4.0.dist-info/WHEEL
sridentify-0.4.0.dist-info/entry_points.txt
sridentify-0.4.0.dist-info/metadata.json
sridentify-0.4.0.dist-info/top_level.txt
