Metadata-Version: 2.0
Name: sridentify
Version: 0.4.0
Summary: Identify the EPSG code from a .prj file
Home-page: https://github.com/cmollet/sridentify
Author: Cory Mollet
Author-email: holla@corymollet.com
License: MIT
Keywords: epsg,gis,shapefile,cli
Platform: UNKNOWN
Classifier: Development Status :: 3 - Alpha
Classifier: Intended Audience :: Developers
Classifier: License :: OSI Approved :: MIT License
Classifier: Natural Language :: English
Classifier: Programming Language :: Python :: 2
Classifier: Programming Language :: Python :: 2.7
Classifier: Programming Language :: Python :: 3
Classifier: Programming Language :: Python :: 3.3
Classifier: Programming Language :: Python :: 3.4
Classifier: Programming Language :: Python :: 3.5
Classifier: Programming Language :: Python :: 3.6
Classifier: Topic :: Scientific/Engineering :: GIS
Classifier: Topic :: Utilities
